<?xml version="1.0" encoding="utf-8"?>
<!DOCTYPE root [
<!ENTITY nbsp "&#160;">
]>
<module_config>
  <package_id>board</package_id>
  <package_name>통합게시판</package_name>
  <module_path>/data/ys_cms/cms/modules/board</module_path>
  <path>/board</path>
  <board_name>모듈샘플</board_name>
  <board_id>default</board_id>
  <table_name>yb_board</table_name>
  <use_multihost>false</use_multihost>
  <skin_style>board</skin_style>
  <list_msg></list_msg>
  <write_msg></write_msg>
  <default_contents></default_contents>
  <use_tag>false</use_tag>
  <use_category_1>false</use_category_1>
  <use_logoff_write>false</use_logoff_write>
  <get_guest_info>false</get_guest_info>
  <use_allow>false</use_allow>
  <use_lock>false</use_lock>
  <lock_default>open</lock_default>
  <file_upload_count>5</file_upload_count>
  <max_size_upload>50</max_size_upload>
  <ext_deny_upload>php,phps,php3,html,htm,phtml,phtm,shtm,shtml,pl,cgi,asp,js,css,swf,exe,inc,ztx,dot</ext_deny_upload>
  <max_size_file>10</max_size_file>
  <ext_photo_file>jpg,gif,png,bmp,jpeg</ext_photo_file>
  <max_size_photo>10</max_size_photo>
  <ext_movie_file>wmv,avi,mpeg,mpg,mp4,mov,flv</ext_movie_file>
  <max_size_movie>50</max_size_movie>
  <use_editor>false</use_editor>
  <use_map>false</use_map>
  <use_write_sms>false</use_write_sms>
  <write_sms_send_number></write_sms_send_number>
  <write_sms_recv_number></write_sms_recv_number>
  <write_sms_mesg>[사이트] 모듈샘플 게시판에 [등록자]님의 글이 등록되었습니다.</write_sms_mesg>
  <use_write_field>false</use_write_field>
  <use_phone_filter>false</use_phone_filter>
  <use_reply>none</use_reply>
  <use_reply_sms>none</use_reply_sms>
  <list_at_view>false</list_at_view>
  <visit_expire_term>60</visit_expire_term>
  <use_comment>false</use_comment>
  <comment_type>normal</comment_type>
  <show_delete>false</show_delete>
  <use_top>false</use_top>
  <page_scale>15</page_scale>
  <block_scale>10</block_scale>
  <subject_cut>35</subject_cut>
  <contents_cut>0</contents_cut>
  <new_article_term>3</new_article_term>
  <use_hide_name>false</use_hide_name>
  <use_search_tag>false</use_search_tag>
  <use_hide_title>false</use_hide_title>
  <writer_display>person</writer_display>
  <use_title_style>false</use_title_style>
  <search_list>
    <_item>title|제목</_item>
    <_item>contents|내용</_item>
    <_item>reg_name|등록자</_item>
    <_item>reg_id|아이디</_item>
  </search_list>
  <add_search>0</add_search>
  <use_process_1>false</use_process_1>
  <process_1>
    <_item>신청</_item>
    <_item>접수</_item>
    <_item>보류</_item>
    <_item>완료</_item>
  </process_1>
  <digitomi>http://njebook.yeosu.go.kr</digitomi>
  <ebook_key>yeosu</ebook_key>
  <digitomi_create_call>/Web/MakerAuto</digitomi_create_call>
  <digitomi_text_return_url>http://njebook.yeosu.go.kr/rise7.php/AutoMaker/textView/</digitomi_text_return_url>
  <digitomi_delete_call_page>/rise7.php/AutoMaker/contentsDelete/</digitomi_delete_call_page>
  <ebook_cover_url>http://njebook.yeosu.go.kr/cover</ebook_cover_url>
  <include_before_upload>/data/yeosu_cms/cms/modules/_plugin/digitomi/upload_before.php</include_before_upload>
  <include_before_write>/data/yeosu_cms/cms/modules/_plugin/digitomi/write_before.php</include_before_write>
  <ebook_return_url_1>http://www.yeosu.go.kr/ybscript.io/plugin/digitomi_result</ebook_return_url_1>
  <ebook_return_url_2>http://www.yeosu.go.kr/ybscript.io/plugin/digitomi_result</ebook_return_url_2>
  <ext_ebook_file>doc,docx,ppt,pptx,xls,xlsx,pdf,hwp</ext_ebook_file>
  <ebook_use>false</ebook_use>
  <ebook_show>false</ebook_show>
  <ebook_cate_code>0</ebook_cate_code>
  <ebook_pw></ebook_pw>
</module_config>
